frc6343/__init__.py
frc6343/controller/deadband.py
frc6343/controller/guitar/guitar.py
frc6343-0.2.dist-info/LICENSE
frc6343-0.2.dist-info/METADATA
frc6343-0.2.dist-info/WHEEL
frc6343-0.2.dist-info/top_level.txt
frc6343-0.2.dist-info/RECORD
